nocodb_simple_client/__init__.py
nocodb_simple_client/api_version.py
nocodb_simple_client/async_client.py
nocodb_simple_client/base_resolver.py
nocodb_simple_client/cache.py
nocodb_simple_client/cli.py
nocodb_simple_client/client.py
nocodb_simple_client/columns.py
nocodb_simple_client/config.py
nocodb_simple_client/exceptions.py
nocodb_simple_client/file_operations.py
nocodb_simple_client/filter_builder.py
nocodb_simple_client/links.py
nocodb_simple_client/meta_client.py
nocodb_simple_client/models.py
nocodb_simple_client/pagination.py
nocodb_simple_client/query_builder.py
nocodb_simple_client/table.py
nocodb_simple_client/validation.py
nocodb_simple_client/views.py
nocodb_simple_client/webhooks.py
nocodb_simple_client-1.3.0.dist-info/METADATA
nocodb_simple_client-1.3.0.dist-info/WHEEL
nocodb_simple_client-1.3.0.dist-info/licenses/LICENSE
nocodb_simple_client-1.3.0.dist-info/RECORD
