Metadata-Version: 2.4
Name: nocodb-simple-client
Version: 1.3.0
Summary: A simple and powerful NocoDB REST API client for Python
Project-URL: Homepage, https://github.com/bauer-group/LIB-NocoDB_SimpleClient
Project-URL: Documentation, https://github.com/bauer-group/LIB-NocoDB_SimpleClient#readme
Project-URL: Repository, https://github.com/bauer-group/LIB-NocoDB_SimpleClient.git
Project-URL: Bug Tracker, https://github.com/bauer-group/LIB-NocoDB_SimpleClient/issues
Project-URL: Changelog, https://github.com/bauer-group/LIB-NocoDB_SimpleClient/blob/main/CHANGELOG.md
Author-email: "BAUER GROUP (Karl Bauer)" <karl.bauer@bauer-group.com>
License-Expression: MIT
License-File: LICENSE
Keywords: api,client,database,low-code,no-code,nocodb,rest
Classifier: Development Status :: 5 - Production/Stable
Classifier: Intended Audience :: Developers
Classifier: License :: OSI Approved :: MIT License
Classifier: Operating System :: OS Independent
Classifier: Programming Language :: Python :: 3
Classifier: Programming Language :: Python :: 3.8
Classifier: Programming Language :: Python :: 3.9
Classifier: Programming Language :: Python :: 3.10
Classifier: Programming Language :: Python :: 3.11
Classifier: Programming Language :: Python :: 3.12
Classifier: Programming Language :: Python :: 3.13
Classifier: Topic :: Database
Classifier: Topic :: Internet :: WWW/HTTP :: Dynamic Content
Classifier: Topic :: Office/Business
Classifier: Topic :: Software Development :: Libraries :: Python Modules
Requires-Python: >=3.8
Requires-Dist: pydantic>=1.8.0
Requires-Dist: requests-toolbelt>=0.9.1
Requires-Dist: requests>=2.25.0
Provides-Extra: dev
Requires-Dist: aiofiles>=0.8.0; extra == 'dev'
Requires-Dist: aiohttp>=3.8.0; extra == 'dev'
Requires-Dist: bandit>=1.7.0; extra == 'dev'
Requires-Dist: black>=22.0.0; extra == 'dev'
Requires-Dist: build>=0.10.0; extra == 'dev'
Requires-Dist: docker>=6.0.0; extra == 'dev'
Requires-Dist: mypy>=1.0.0; extra == 'dev'
Requires-Dist: pillow>=10.0.0; extra == 'dev'
Requires-Dist: pre-commit>=2.20.0; extra == 'dev'
Requires-Dist: pytest-asyncio>=0.23.0; extra == 'dev'
Requires-Dist: pytest-benchmark>=4.0.0; extra == 'dev'
Requires-Dist: pytest-cov>=4.0.0; extra == 'dev'
Requires-Dist: pytest-xdist>=3.0.0; extra == 'dev'
Requires-Dist: pytest>=7.0.0; extra == 'dev'
Requires-Dist: python-dotenv>=1.0.0; extra == 'dev'
Requires-Dist: python-semantic-release>=8.0.0; extra == 'dev'
Requires-Dist: ruff>=0.1.0; extra == 'dev'
Requires-Dist: safety>=2.0.0; extra == 'dev'
Requires-Dist: tomli>=2.0.0; (python_version < '3.11') and extra == 'dev'
Requires-Dist: tox>=4.0.0; extra == 'dev'
Requires-Dist: twine>=4.0.0; extra == 'dev'
Requires-Dist: types-aiofiles>=0.8.0; extra == 'dev'
Requires-Dist: types-pyyaml>=6.0.0; extra == 'dev'
Requires-Dist: types-requests>=2.31.0; extra == 'dev'
Provides-Extra: docs
Requires-Dist: mkdocs-autorefs>=0.4.1; extra == 'docs'
Requires-Dist: mkdocs-material>=8.5.0; extra == 'docs'
Requires-Dist: mkdocs>=1.4.0; extra == 'docs'
Requires-Dist: mkdocstrings[python]>=0.19.0; extra == 'docs'
